{
    "build" : {
        "build": {
            "neuron_path": "../nrn-7.2",
            "specials_path": "../specials"
        },
        "build_config": {
            "options": [
              "--without-iv",
              "--without-x"
            ],
            "compile_options": {
              "CC": "gcc",
              "CXX": "g++"
            }
        }
    },
    "job" : {
        "type": "cluster",
        "job_cluster": {
            "modules": [
            ],
            "omp_num_threads": 16,
            "nrniv": "../specials/x86_64/special -mpi",
            "hoc_name": "../hoc/bench_main.hoc",
            "stop_time": 200,
            "nthread": 16,
            "prof": ""
        }
    }
}
